streamlit_lightweight_charts_ntf/__init__.py
streamlit_lightweight_charts_ntf/frontend/build/asset-manifest.json
streamlit_lightweight_charts_ntf/frontend/build/index.html
streamlit_lightweight_charts_ntf/frontend/build/precache-manifest.1e532743f3e0ab6741499b7f9ba52e99.js
streamlit_lightweight_charts_ntf/frontend/build/precache-manifest.3e5867b426fc68dea3b4139343c25ce7.js
streamlit_lightweight_charts_ntf/frontend/build/precache-manifest.9a0c5df07df38e2027756eb38d3edc76.js
streamlit_lightweight_charts_ntf/frontend/build/service-worker.js
streamlit_lightweight_charts_ntf/frontend/build/static/js/2.70fc4790.chunk.js
streamlit_lightweight_charts_ntf/frontend/build/static/js/2.70fc4790.chunk.js.LICENSE.txt
streamlit_lightweight_charts_ntf/frontend/build/static/js/2.70fc4790.chunk.js.map
streamlit_lightweight_charts_ntf/frontend/build/static/js/2.e1783641.chunk.js
streamlit_lightweight_charts_ntf/frontend/build/static/js/2.e1783641.chunk.js.LICENSE.txt
streamlit_lightweight_charts_ntf/frontend/build/static/js/2.e1783641.chunk.js.map
streamlit_lightweight_charts_ntf/frontend/build/static/js/main.38db1b64.chunk.js
streamlit_lightweight_charts_ntf/frontend/build/static/js/main.38db1b64.chunk.js.map
streamlit_lightweight_charts_ntf/frontend/build/static/js/main.4e617eae.chunk.js
streamlit_lightweight_charts_ntf/frontend/build/static/js/main.4e617eae.chunk.js.map
streamlit_lightweight_charts_ntf/frontend/build/static/js/main.e3a393b7.chunk.js
streamlit_lightweight_charts_ntf/frontend/build/static/js/main.e3a393b7.chunk.js.map
streamlit_lightweight_charts_ntf/frontend/build/static/js/runtime-main.938d375b.js
streamlit_lightweight_charts_ntf/frontend/build/static/js/runtime-main.938d375b.js.map
streamlit_lightweight_charts_ntf-0.8.12.dist-info/METADATA
streamlit_lightweight_charts_ntf-0.8.12.dist-info/WHEEL
streamlit_lightweight_charts_ntf-0.8.12.dist-info/top_level.txt
streamlit_lightweight_charts_ntf-0.8.12.dist-info/RECORD
