Metadata-Version: 2.1
Name: streamlit-lightweight-charts-ntf
Version: 0.8.12
Summary: Wrapper for TradingView lightweight-charts using ntf fork
Home-page: https://github.com/freyastreamlit/streamlit-lightweight-charts-ntf
Author: Joe Rosa
Author-email: joe.rosa@itpmngt.co.uk
License: MIT
Platform: UNKNOWN
Classifier: License :: OSI Approved :: MIT License
Classifier: Programming Language :: Python :: 3
Classifier: Programming Language :: Python :: 3.6
Requires-Python: >=3.6
